qagentic/__init__.py
qagentic/cli.py
qagentic/py.typed
qagentic/pytest_plugin.py
qagentic/core/__init__.py
qagentic/core/attachments.py
qagentic/core/config.py
qagentic/core/context.py
qagentic/core/decorators.py
qagentic/core/reporter.py
qagentic/core/severity.py
qagentic/core/status.py
qagentic/core/test_result.py
qagentic/templates/conftest_template.py
qagentic_pytest-0.1.7.dist-info/METADATA
qagentic_pytest-0.1.7.dist-info/WHEEL
qagentic_pytest-0.1.7.dist-info/entry_points.txt
qagentic_pytest-0.1.7.dist-info/RECORD
