Metadata-Version: 2.4
Name: qagentic-pytest
Version: 0.1.7
Summary: AI-Powered Test Intelligence SDK for Python - pytest plugin with automatic failure analysis
Project-URL: Homepage, https://github.com/qagentic/qagentic-sdk
Project-URL: Documentation, https://docs.qagentic.io
Project-URL: Repository, https://github.com/qagentic/qagentic-sdk
Project-URL: Issues, https://github.com/qagentic/qagentic-sdk/issues
Author-email: QAagentic Team <team@qagentic.io>
License-Expression: MIT
Keywords: ai,allure,automation,pytest,quality-assurance,test-analytics,test-reporting,testing
Classifier: Development Status :: 4 - Beta
Classifier: Framework :: Pytest
Classifier: Intended Audience :: Developers
Classifier: License :: OSI Approved :: MIT License
Classifier: Operating System :: OS Independent
Classifier: Programming Language :: Python :: 3
Classifier: Programming Language :: Python :: 3.8
Classifier: Programming Language :: Python :: 3.9
Classifier: Programming Language :: Python :: 3.10
Classifier: Programming Language :: Python :: 3.11
Classifier: Programming Language :: Python :: 3.12
Classifier: Topic :: Software Development :: Quality Assurance
Classifier: Topic :: Software Development :: Testing
Requires-Python: >=3.8
Requires-Dist: click>=8.0.0
Requires-Dist: httpx>=0.24.0
Requires-Dist: pydantic>=2.0.0
Requires-Dist: pytest>=7.0.0
Requires-Dist: python-dateutil>=2.8.0
Requires-Dist: pyyaml>=6.0
Requires-Dist: rich>=13.0.0
Provides-Extra: dev
Requires-Dist: black>=23.0.0; extra == 'dev'
Requires-Dist: mypy>=1.0.0; extra == 'dev'
Requires-Dist: pytest-cov>=4.0.0; extra == 'dev'
Requires-Dist: ruff>=0.1.0; extra == 'dev'
